utfn/__init__.py
utfn/__main__.py
utfn/utfn.py
UtfN-1.0.1.dist-info/LICENSE
UtfN-1.0.1.dist-info/METADATA
UtfN-1.0.1.dist-info/WHEEL
UtfN-1.0.1.dist-info/dependency_links.txt
UtfN-1.0.1.dist-info/entry_points.txt
UtfN-1.0.1.dist-info/top_level.txt
UtfN-1.0.1.dist-info/RECORD
