Metadata-Version: 2.1
Name: UtfN
Version: 1.0.1
Summary: UNIX time from NTP or short UtfN is a simple CLI tool to set the time from an NTP-Server.
Home-page: https://github.com/datalexum/UNIX-time-from-NTP/
Author: Alexander Schröder
Author-email: alexander.schroeder-t59@rub.de
License: MIT
Download-URL: https://codeload.github.com/datalexum/UNIX-time-from-NTP/tar.gz/refs/tags/1.0.1
Platform: UNKNOWN
Classifier: License :: OSI Approved :: MIT License
Classifier: Programming Language :: Python :: 3
Classifier: Programming Language :: Python :: 3.8
Requires-Python: >=3
Requires-Dist: ntplib
